gz7math/__init__.py
gz7math/gz7math.py
gz7math-0.1.1.dist-info/METADATA
gz7math-0.1.1.dist-info/WHEEL
gz7math-0.1.1.dist-info/top_level.txt
gz7math-0.1.1.dist-info/RECORD
