Metadata-Version: 2.4
Name: gz7math
Version: 0.1.1
Summary: Mathematical functions for the GZ7 angular system by Zaid Emad
Home-page: https://github.com/zaideam90/gz7math
Author: Zaid Emad
Author-email: zaid.eam90@gmail.com
Classifier: Programming Language :: Python :: 3
Classifier: License :: OSI Approved :: MIT License
Classifier: Operating System :: OS Independent
Requires-Python: >=3.6
Dynamic: author
Dynamic: author-email
Dynamic: classifier
Dynamic: description
Dynamic: description-content-type
Dynamic: home-page
Dynamic: requires-python
Dynamic: summary
